cutters-0.1.4.dist-info/METADATA
cutters-0.1.4.dist-info/WHEEL
cutters/__init__.py
cutters/cutters.pypy37-pp73-aarch64-linux-gnu.so
cutters-0.1.4.dist-info/RECORD
