Metadata-Version: 2.1
Name: cutters
Version: 0.1.4
Classifier: Natural Language :: Croatian
Classifier: Natural Language :: English
Classifier: Topic :: Text Processing
Summary: A rule based sentence segmentation library.
Author: cyanic-selkie <cyanic-selkie@protonmail.com>
Author-email: cyanic-selkie <cyanic-selkie@protonmail.com>
License: MIT
Project-URL: Repository, https://github.com/cyanic-selkie/cutters
